django_google_sso/__init__.py
django_google_sso/admin.py
django_google_sso/apps.py
django_google_sso/checks/__init__.py
django_google_sso/checks/warnings.py
django_google_sso/conf.py
django_google_sso/helpers.py
django_google_sso/hooks.py
django_google_sso/main.py
django_google_sso/migrations/0001_initial.py
django_google_sso/migrations/0002_alter_googlessouser_picture_url.py
django_google_sso/migrations/__init__.py
django_google_sso/models.py
django_google_sso/static/django_google_sso/google_button.css
django_google_sso/templates/google_sso/login.html
django_google_sso/templates/google_sso/login_sso.html
django_google_sso/templatetags/__init__.py
django_google_sso/templatetags/show_form.py
django_google_sso/templatetags/sso_tags.py
django_google_sso/tests/__init__.py
django_google_sso/tests/conftest.py
django_google_sso/tests/test_callables.py
django_google_sso/tests/test_conf.py
django_google_sso/tests/test_google_auth.py
django_google_sso/tests/test_models.py
django_google_sso/tests/test_sites.py
django_google_sso/tests/test_tags.py
django_google_sso/tests/test_user_helper.py
django_google_sso/tests/test_views.py
django_google_sso/urls.py
django_google_sso/utils.py
django_google_sso/views.py
django_google_sso-9.0.2.dist-info/METADATA
django_google_sso-9.0.2.dist-info/WHEEL
django_google_sso-9.0.2.dist-info/licenses/LICENSE
django_google_sso-9.0.2.dist-info/RECORD
